<?xml version="1.0" ?>
<annotation>
  <folder>images</folder>
  <filename>329_1_100560_20150105001020001</filename>
  <path>augmented_data/329_1_100560_20150105001020001.jpg</path>
  <source>
    <database>Unknown</database>
  </source>
  <size>
    <width>565</width>
    <height>485</height>
    <depth>3</depth>
  </size>
  <segmented>0</segmented>
  <object>
    <name>Polyp</name>
    <pose>Unspecified</pose>
    <truncated>0</truncated>
    <difficult>0</difficult>
    <confidence>1.0</confidence>
    <bndbox>
      <xmin>326</xmin>
      <ymin>215</ymin>
      <xmax>384</xmax>
      <ymax>270</ymax>
    </bndbox>
  </object>
</annotation>
