<?xml version="1.0" ?>
<annotation>
  <folder>images</folder>
  <filename>365_3_100178_20150106001015009</filename>
  <path>augmented_data/365_3_100178_20150106001015009.jpg</path>
  <source>
    <database>Unknown</database>
  </source>
  <size>
    <width>565</width>
    <height>485</height>
    <depth>3</depth>
  </size>
  <segmented>0</segmented>
  <object>
    <name>Polyp</name>
    <pose>Unspecified</pose>
    <truncated>0</truncated>
    <difficult>0</difficult>
    <confidence>1.0</confidence>
    <bndbox>
      <xmin>427</xmin>
      <ymin>225</ymin>
      <xmax>480</xmax>
      <ymax>288</ymax>
    </bndbox>
  </object>
</annotation>
